flojoy/CONSTANTS.py
flojoy/__init__.py
flojoy/__init__.pyi
flojoy/_logging.py
flojoy/config.py
flojoy/connection_manager.py
flojoy/dao.py
flojoy/data_container.py
flojoy/env_var.py
flojoy/flojoy_instruction.py
flojoy/flojoy_node_venv.py
flojoy/flojoy_python.py
flojoy/instruments/__init__.py
flojoy/instruments/tektronix/MDO30xx.py
flojoy/instruments/tektronix/RSA_API.py
flojoy/instruments/tektronix/__init__.py
flojoy/job_result_builder.py
flojoy/job_result_utils.py
flojoy/job_service.py
flojoy/models/JobResults/JobFailure.py
flojoy/models/JobResults/JobFeedback.py
flojoy/models/JobResults/JobSuccess.py
flojoy/models/JobResults/__init__.py
flojoy/models/__init__.py
flojoy/module_scraper.py
flojoy/node_init.py
flojoy/node_preflight.py
flojoy/parameter_types.py
flojoy/plotly_utils.py
flojoy/reconciler.py
flojoy/small_memory.py
flojoy/utils.py
flojoy-0.4.1.dist-info/LICENSE.txt
flojoy-0.4.1.dist-info/METADATA
flojoy-0.4.1.dist-info/WHEEL
flojoy-0.4.1.dist-info/RECORD
