Metadata-Version: 2.1
Name: flojoy
Version: 0.4.1
Summary: 
Author: Jack Palmer
Author-email: jp@flojoy.io
Requires-Python: >=3.11,<3.12
Classifier: Programming Language :: Python :: 3
Classifier: Programming Language :: Python :: 3.11
Requires-Dist: cloudpickle (>=2,<3)
Requires-Dist: httpx (>=0.26.0,<0.27.0)
Requires-Dist: huggingface-hub (>=0,<1)
Requires-Dist: keyring (>=24,<25)
Requires-Dist: keyrings-cryptfile (>=1.3.9,<2.0.0)
Requires-Dist: matplotlib (>=3,<4)
Requires-Dist: networkx (>=3,<4)
Requires-Dist: numpy (>=1,<2)
Requires-Dist: pandas (>=2,<3)
Requires-Dist: pillow (>=10,<11)
Requires-Dist: plotly (>=5,<6)
Requires-Dist: portalocker (>=2,<3)
Requires-Dist: pydantic (>=2,<3)
Requires-Dist: python-box (>=7,<8)
Requires-Dist: python-dotenv (>=1,<2)
Requires-Dist: pyyaml (>=6.0,<6.1)
Requires-Dist: qcodes (>=0,<1)
Requires-Dist: requests (>=2,<3)
Requires-Dist: scipy (>=1.12,<1.13)
Requires-Dist: tm-devices (>=1.0.0,<2.0.0)
